LICENSE.txt
MANIFEST.in
README.md
setup.py
askcode/__init__.py
askcode/__main__.py
askcode/ascode-ultra.py
askcode/factorial.py
askcode/gitllm.py
askcode/new.py
askcode.egg-info/PKG-INFO
askcode.egg-info/SOURCES.txt
askcode.egg-info/dependency_links.txt
askcode.egg-info/entry_points.txt
askcode.egg-info/requires.txt
askcode.egg-info/top_level.txt